data_degradation_detector/__init__.py
data_degradation_detector/multivariate.py
data_degradation_detector/report.py
data_degradation_detector/univariate.py
data_degradation_detector-1.0.6.dist-info/licenses/LICENSE
data_degradation_detector-1.0.6.dist-info/METADATA
data_degradation_detector-1.0.6.dist-info/WHEEL
data_degradation_detector-1.0.6.dist-info/top_level.txt
data_degradation_detector-1.0.6.dist-info/RECORD
